README.md
setup.py
opauth_jwt/__init__.py
opauth_jwt/backends.py
opauth_jwt/settings.py
opauth_jwt.egg-info/PKG-INFO
opauth_jwt.egg-info/SOURCES.txt
opauth_jwt.egg-info/dependency_links.txt
opauth_jwt.egg-info/requires.txt
opauth_jwt.egg-info/top_level.txt
opauth_jwt/utils/__init__.py
opauth_jwt/utils/decorators.py
opauth_jwt/utils/exception.py
opauth_jwt/utils/jwt_auth.py
opauth_jwt/utils/string_util.py