Metadata-Version: 1.0
Name: opauth-jwt
Version: 1.0.1
Summary: 描述
Home-page: https://github.com/ruoxing
Author: ruoxing
Author-email: 15085751956@163.com
License: MIT Licence
Keywords: deppon,ruoxing,jwt
Platform: any
